cowsay/__init__.py
cowsay/__main__.py
cowsay/cows/TuxStab.cow
cowsay/cows/beavis.zen.cow
cowsay/cows/blowfish.cow
cowsay/cows/bong.cow
cowsay/cows/bud-frogs.cow
cowsay/cows/bunny.cow
cowsay/cows/cheese.cow
cowsay/cows/cower.cow
cowsay/cows/daemon.cow
cowsay/cows/default.cow
cowsay/cows/dragon-and-cow.cow
cowsay/cows/dragon.cow
cowsay/cows/elephant-in-snake.cow
cowsay/cows/elephant.cow
cowsay/cows/eyes.cow
cowsay/cows/flaming-sheep.cow
cowsay/cows/frogs.cow
cowsay/cows/ghostbusters.cow
cowsay/cows/head-in.cow
cowsay/cows/hellokitty.cow
cowsay/cows/kiss.cow
cowsay/cows/kitty.cow
cowsay/cows/koala.cow
cowsay/cows/kosh.cow
cowsay/cows/luke-koala.cow
cowsay/cows/meow.cow
cowsay/cows/milk.cow
cowsay/cows/moofasa.cow
cowsay/cows/moose.cow
cowsay/cows/mutilated.cow
cowsay/cows/ren.cow
cowsay/cows/satanic.cow
cowsay/cows/sheep.cow
cowsay/cows/skeleton.cow
cowsay/cows/small.cow
cowsay/cows/stegosaurus.cow
cowsay/cows/stimpy.cow
cowsay/cows/supermilker.cow
cowsay/cows/surgery.cow
cowsay/cows/three-eyes.cow
cowsay/cows/turkey.cow
cowsay/cows/turtle.cow
cowsay/cows/tux.cow
cowsay/cows/udder.cow
cowsay/cows/vader-koala.cow
cowsay/cows/vader.cow
cowsay/cows/www.cow
python_cowsay-1.2.2.dist-info/licenses/LICENSE
python_cowsay-1.2.2.dist-info/METADATA
python_cowsay-1.2.2.dist-info/WHEEL
python_cowsay-1.2.2.dist-info/entry_points.txt
python_cowsay-1.2.2.dist-info/top_level.txt
python_cowsay-1.2.2.dist-info/RECORD
