Metadata-Version: 2.4
Name: python-cowsay
Version: 1.2.2
Summary: A Cowsay clone in Python
Author: James Finnie-Ansley
License-Expression: GPL-3.0-or-later
Project-URL: repository, https://codeberg.org/jamesansley/cowsay
Keywords: cowsay
Classifier: Development Status :: 5 - Production/Stable
Classifier: Topic :: Utilities
Classifier: Intended Audience :: Developers
Classifier: Programming Language :: Python :: 3
Requires-Python: >=3.8
License-File: LICENSE
Dynamic: license-file
